<keymap version="1" name="Default copy" parent="$default">
  <action id="CloseContent">
    <keyboard-shortcut first-keystroke="ctrl f4" />
    <keyboard-shortcut first-keystroke="ctrl w" />
  </action>
  <action id="Console.Execute.Multiline" />
  <action id="EditorDuplicate">
    <keyboard-shortcut first-keystroke="ctrl d" />
    <keyboard-shortcut first-keystroke="ctrl enter" />
  </action>
  <action id="EditorSelectWord" />
  <action id="EditorSplitLine" />
  <action id="Mongo.Shell.Execute" />
  <action id="RunCommandAction" />
  <action id="ScanKeysAction" />
  <action id="ViewSource" />
</keymap>